{
  "cli": {
    "version": ">=16.0.0",
    "appVersionSource": "remote"
  },
  "build": {
    "production": {
      "android": {
        "buildType": "app-bundle"},
      "distribution": "internal",
      "channel": "production",
      "env": {
        "EXPO_USE_FAST_RESOLVER": "1"}
    },
    "preview": {
      "distribution": "internal",
      "android": {
        "buildType": "app-bundle"
      }
    },
    "production": {
      "autoIncrement": true,
      "android": {
        "buildType": "app-bundle"
      }
    }
  },
  "updates": {
      "url": "https://u.expo.dev/de3329e9-ed7a-4005-abfa-7bda2599b5d4"},
  "submit": {
    "production": {}
  }
}
